pyebm/__init__.py
pyebm/core_utilities.py
pyebm/debm.py
pyebm/ebm.py
pyebm/load_dataset.py
pyebm/central_ordering/__init__.py
pyebm/central_ordering/data_likelihood.py
pyebm/central_ordering/generalized_mallows.py
pyebm/inputs_outputs/__init__.py
pyebm/inputs_outputs/prepare_inputs.py
pyebm/inputs_outputs/prepare_outputs.py
pyebm/inputs_outputs/visualize.py
pyebm/mixture_model/__init__.py
pyebm/mixture_model/do_classification.py
pyebm/mixture_model/gaussian_mixture_model.py
pyebm-2.0.3.dist-info/LICENSE
pyebm-2.0.3.dist-info/METADATA
pyebm-2.0.3.dist-info/WHEEL
pyebm-2.0.3.dist-info/top_level.txt
pyebm-2.0.3.dist-info/RECORD
