Metadata-Version: 2.1
Name: pyebm
Version: 2.0.3
Summary: Toolbox for event-based modeling
Home-page: https://github.com/88vikram/pyebm/
Author: Vikram Venkatraghavan
Author-email: v.venkatraghavan@erasmusmc.nl
License: UNKNOWN
Platform: UNKNOWN
Classifier: Programming Language :: Python :: 3
Classifier: License :: OSI Approved :: GNU General Public License v3 or later (GPLv3+)
Classifier: Operating System :: OS Independent
Requires-Dist: numpy
Requires-Dist: pandas
Requires-Dist: scikit-learn
Requires-Dist: scipy
Requires-Dist: six
Requires-Dist: statsmodels
Requires-Dist: matplotlib
Requires-Dist: seaborn
Requires-Dist: requests
Requires-Dist: tqdm
